{
  "saveNumber": 5,
  "gameMetadata": {
    "gameMode": 3,
    "trainingMode": true,
    "player1Playstyle": "Spears",
    "player2Playstyle": "Spears",
    "currentPhase": 3,
    "currentRound": 20,
    "isPlayer1Turn": true,
    "lastAction": {
      "playerName": "AI_P1",
      "actionType": "0",
      "cardName": "Arsenal",
      "round": 20,
      "phase": 3,
      "effectsApplied": [
        "getShieldPoints"

      ]

    }

  },
  "board": {
    "pawnPosition": 4,
    "pawnTrack": "0000000000100000000"

  },
  "progressTokens": [
    {
      "name": "Mathematics",
      "description": "At the end of the game score 3 victory points for each Progress token in your possession (including itself)",
      "victoryPoints": 0,
      "shieldPoints": 0
    },
    {
      "name": "Agriculture",
      "description": "Take 6 coins from the bank",
      "victoryPoints": 4,
      "shieldPoints": 0
    },
    {
      "name": "Urbanism",
      "description": "Immediately take 6 coins from the Bank. Each time you construct a Building for free through linking (free construction condition chain) you gain 4 coins",
      "victoryPoints": 0,
      "shieldPoints": 0
    },
    {
      "name": "Philosophy",
      "description": "The token is worth 7 victory points.",
      "victoryPoints": 7,
      "shieldPoints": 0
    }

  ],
  "militaryTokens": [

  ],
  "age1Tree": [
    {
      "index": 0,
      "cardName": "EMPTY",
      "isEmpty": true,
      "isAvailable": false,
      "isVisible": false,
      "parents": []
    },
    {
      "index": 1,
      "cardName": "EMPTY",
      "isEmpty": true,
      "isAvailable": false,
      "isVisible": false,
      "parents": []
    },
    {
      "index": 2,
      "cardName": "EMPTY",
      "isEmpty": true,
      "isAvailable": false,
      "isVisible": false,
      "parents": [0, 0]
    },
    {
      "index": 3,
      "cardName": "EMPTY",
      "isEmpty": true,
      "isAvailable": false,
      "isVisible": false,
      "parents": [0, 1]
    },
    {
      "index": 4,
      "cardName": "EMPTY",
      "isEmpty": true,
      "isAvailable": false,
      "isVisible": false,
      "parents": [1, 1]
    },
    {
      "index": 5,
      "cardName": "EMPTY",
      "isEmpty": true,
      "isAvailable": false,
      "isVisible": false,
      "parents": [2, 2]
    },
    {
      "index": 6,
      "cardName": "EMPTY",
      "isEmpty": true,
      "isAvailable": false,
      "isVisible": false,
      "parents": [2, 3]
    },
    {
      "index": 7,
      "cardName": "EMPTY",
      "isEmpty": true,
      "isAvailable": false,
      "isVisible": false,
      "parents": [3, 4]
    },
    {
      "index": 8,
      "cardName": "EMPTY",
      "isEmpty": true,
      "isAvailable": false,
      "isVisible": false,
      "parents": [4, 4]
    },
    {
      "index": 9,
      "cardName": "EMPTY",
      "isEmpty": true,
      "isAvailable": false,
      "isVisible": false,
      "parents": [5, 5]
    },
    {
      "index": 10,
      "cardName": "EMPTY",
      "isEmpty": true,
      "isAvailable": false,
      "isVisible": false,
      "parents": [5, 6]
    },
    {
      "index": 11,
      "cardName": "EMPTY",
      "isEmpty": true,
      "isAvailable": false,
      "isVisible": false,
      "parents": [6, 7]
    },
    {
      "index": 12,
      "cardName": "EMPTY",
      "isEmpty": true,
      "isAvailable": false,
      "isVisible": false,
      "parents": [7, 8]
    },
    {
      "index": 13,
      "cardName": "EMPTY",
      "isEmpty": true,
      "isAvailable": false,
      "isVisible": false,
      "parents": [8, 8]
    },
    {
      "index": 14,
      "cardName": "EMPTY",
      "isEmpty": true,
      "isAvailable": false,
      "isVisible": false,
      "parents": [9, 9]
    },
    {
      "index": 15,
      "cardName": "EMPTY",
      "isEmpty": true,
      "isAvailable": false,
      "isVisible": false,
      "parents": [9, 10]
    },
    {
      "index": 16,
      "cardName": "EMPTY",
      "isEmpty": true,
      "isAvailable": false,
      "isVisible": false,
      "parents": [10, 11]
    },
    {
      "index": 17,
      "cardName": "EMPTY",
      "isEmpty": true,
      "isAvailable": false,
      "isVisible": false,
      "parents": [11, 12]
    },
    {
      "index": 18,
      "cardName": "EMPTY",
      "isEmpty": true,
      "isAvailable": false,
      "isVisible": false,
      "parents": [12, 13]
    },
    {
      "index": 19,
      "cardName": "EMPTY",
      "isEmpty": true,
      "isAvailable": false,
      "isVisible": false,
      "parents": [13, 13]
    }

  ],
  "age2Tree": [
    {
      "index": 0,
      "cardName": "EMPTY",
      "isEmpty": true,
      "isAvailable": false,
      "isVisible": false,
      "parents": []
    },
    {
      "index": 1,
      "cardName": "EMPTY",
      "isEmpty": true,
      "isAvailable": false,
      "isVisible": false,
      "parents": []
    },
    {
      "index": 2,
      "cardName": "EMPTY",
      "isEmpty": true,
      "isAvailable": false,
      "isVisible": false,
      "parents": []
    },
    {
      "index": 3,
      "cardName": "EMPTY",
      "isEmpty": true,
      "isAvailable": false,
      "isVisible": false,
      "parents": []
    },
    {
      "index": 4,
      "cardName": "EMPTY",
      "isEmpty": true,
      "isAvailable": false,
      "isVisible": false,
      "parents": []
    },
    {
      "index": 5,
      "cardName": "EMPTY",
      "isEmpty": true,
      "isAvailable": false,
      "isVisible": false,
      "parents": []
    },
    {
      "index": 6,
      "cardName": "EMPTY",
      "isEmpty": true,
      "isAvailable": false,
      "isVisible": false,
      "parents": [0, 1]
    },
    {
      "index": 7,
      "cardName": "EMPTY",
      "isEmpty": true,
      "isAvailable": false,
      "isVisible": false,
      "parents": [1, 2]
    },
    {
      "index": 8,
      "cardName": "EMPTY",
      "isEmpty": true,
      "isAvailable": false,
      "isVisible": false,
      "parents": [2, 3]
    },
    {
      "index": 9,
      "cardName": "EMPTY",
      "isEmpty": true,
      "isAvailable": false,
      "isVisible": false,
      "parents": [3, 4]
    },
    {
      "index": 10,
      "cardName": "EMPTY",
      "isEmpty": true,
      "isAvailable": false,
      "isVisible": false,
      "parents": [4, 5]
    },
    {
      "index": 11,
      "cardName": "EMPTY",
      "isEmpty": true,
      "isAvailable": false,
      "isVisible": false,
      "parents": [6, 7]
    },
    {
      "index": 12,
      "cardName": "EMPTY",
      "isEmpty": true,
      "isAvailable": false,
      "isVisible": false,
      "parents": [7, 8]
    },
    {
      "index": 13,
      "cardName": "EMPTY",
      "isEmpty": true,
      "isAvailable": false,
      "isVisible": false,
      "parents": [8, 9]
    },
    {
      "index": 14,
      "cardName": "EMPTY",
      "isEmpty": true,
      "isAvailable": false,
      "isVisible": false,
      "parents": [9, 10]
    },
    {
      "index": 15,
      "cardName": "EMPTY",
      "isEmpty": true,
      "isAvailable": false,
      "isVisible": false,
      "parents": [11, 12]
    },
    {
      "index": 16,
      "cardName": "EMPTY",
      "isEmpty": true,
      "isAvailable": false,
      "isVisible": false,
      "parents": [12, 13]
    },
    {
      "index": 17,
      "cardName": "EMPTY",
      "isEmpty": true,
      "isAvailable": false,
      "isVisible": false,
      "parents": [13, 14]
    },
    {
      "index": 18,
      "cardName": "EMPTY",
      "isEmpty": true,
      "isAvailable": false,
      "isVisible": false,
      "parents": [15, 16]
    },
    {
      "index": 19,
      "cardName": "EMPTY",
      "isEmpty": true,
      "isAvailable": false,
      "isVisible": false,
      "parents": [16, 17]
    }

  ],
  "age3Tree": [
    {
      "index": 0,
      "cardName": "EMPTY",
      "isEmpty": true,
      "isAvailable": false,
      "isVisible": false,
      "parents": []
    },
    {
      "index": 1,
      "cardName": "EMPTY",
      "isEmpty": true,
      "isAvailable": false,
      "isVisible": false,
      "parents": []
    },
    {
      "index": 2,
      "cardName": "EMPTY",
      "isEmpty": true,
      "isAvailable": false,
      "isVisible": false,
      "parents": [0, 0]
    },
    {
      "index": 3,
      "cardName": "EMPTY",
      "isEmpty": true,
      "isAvailable": false,
      "isVisible": false,
      "parents": [0, 1]
    },
    {
      "index": 4,
      "cardName": "EMPTY",
      "isEmpty": true,
      "isAvailable": false,
      "isVisible": false,
      "parents": [1, 1]
    },
    {
      "index": 5,
      "cardName": "EMPTY",
      "isEmpty": true,
      "isAvailable": false,
      "isVisible": false,
      "parents": [2, 2]
    },
    {
      "index": 6,
      "cardName": "EMPTY",
      "isEmpty": true,
      "isAvailable": false,
      "isVisible": false,
      "parents": [2, 3]
    },
    {
      "index": 7,
      "cardName": "EMPTY",
      "isEmpty": true,
      "isAvailable": false,
      "isVisible": false,
      "parents": [3, 4]
    },
    {
      "index": 8,
      "cardName": "EMPTY",
      "isEmpty": true,
      "isAvailable": false,
      "isVisible": false,
      "parents": [4, 4]
    },
    {
      "index": 9,
      "cardName": "EMPTY",
      "isEmpty": true,
      "isAvailable": false,
      "isVisible": false,
      "parents": [5, 6]
    },
    {
      "index": 10,
      "cardName": "EMPTY",
      "isEmpty": true,
      "isAvailable": false,
      "isVisible": false,
      "parents": [7, 8]
    },
    {
      "index": 11,
      "cardName": "EMPTY",
      "isEmpty": true,
      "isAvailable": false,
      "isVisible": false,
      "parents": [9, 9]
    },
    {
      "index": 12,
      "cardName": "EMPTY",
      "isEmpty": true,
      "isAvailable": false,
      "isVisible": false,
      "parents": [9, 9]
    },
    {
      "index": 13,
      "cardName": "EMPTY",
      "isEmpty": true,
      "isAvailable": false,
      "isVisible": false,
      "parents": [10, 10]
    },
    {
      "index": 14,
      "cardName": "EMPTY",
      "isEmpty": true,
      "isAvailable": false,
      "isVisible": false,
      "parents": [10, 10]
    },
    {
      "index": 15,
      "cardName": "EMPTY",
      "isEmpty": true,
      "isAvailable": false,
      "isVisible": false,
      "parents": [11, 12]
    },
    {
      "index": 16,
      "cardName": "EMPTY",
      "isEmpty": true,
      "isAvailable": false,
      "isVisible": false,
      "parents": [12, 13]
    },
    {
      "index": 17,
      "cardName": "EMPTY",
      "isEmpty": true,
      "isAvailable": false,
      "isVisible": false,
      "parents": [13, 14]
    },
    {
      "index": 18,
      "cardName": "EMPTY",
      "isEmpty": true,
      "isAvailable": false,
      "isVisible": false,
      "parents": [15, 16]
    },
    {
      "index": 19,
      "cardName": "EMPTY",
      "isEmpty": true,
      "isAvailable": false,
      "isVisible": false,
      "parents": [16, 17]
    }

  ],
  "player1": {
    "id": 1,
    "username": "AI_P1",
    "remainingCoins": {"gold": 0, "silver": 1, "bronze": 2},
    "totalCoins": 15,
    "permanentResources": [
      {"type": "GLASS", "amount": 4},
      {"type": "STONE", "amount": 2},
      {"type": "WOOD", "amount": 2},
      {"type": "PAPYRUS", "amount": 2},
      {"type": "CLAY", "amount": 4}

    ],
    "tradingResources": [

    ],
    "scientificSymbols": [
      {"type": "FEATHER", "amount": 2},
      {"type": "MOJAR", "amount": 1},
      {"type": "PENDULUM", "amount": 1},
      {"type": "GLOBE", "amount": 1}

    ],
    "tradeRules": [
      "Wood"

    ],
    "tokensOwnedBitset": "0000000000",
    "builtCards": [
      "Altar",
      "Scriptorium",
      "Guard Tower",
      "Stable",
      "Wood Reserve",
      "Pharmacist",
      "Press",
      "Caravansery",
      "Library",
      "Brickyard",
      "Courthouse",
      "Barracks",
      "Laboratory",
      "Horse Breeders",
      "Glass-Blower",
      "Arena",
      "Observatory",
      "Lumber Yard",
      "Tacticians Guild",
      "Pretorium",
      "Obelisk",
      "Arsenal"

    ],
    "wonders": [
      "The Mausoleum",
      "The Pyramids",
      "The Temple of Artemis"

    ],
    "ownedTokens": [
      "Military Loss 5",
      "Masonry"

    ],
    "points": {
      "military": 10,
      "building": 54,
      "wonder": 0,
      "progress": 0,
      "total": 64

    }

  },
  "player2": {
    "id": 2,
    "username": "AI_P2",
    "remainingCoins": {"gold": 2, "silver": 1, "bronze": 1},
    "totalCoins": 11,
    "permanentResources": [
      {"type": "CLAY", "amount": 5},
      {"type": "STONE", "amount": 1},
      {"type": "WOOD", "amount": 4}

    ],
    "tradingResources": [

    ],
    "scientificSymbols": [
      {"type": "PENDULUM", "amount": 1},
      {"type": "MOJAR", "amount": 1}

    ],
    "tradeRules": [
      "Clay",
      "Stone"

    ],
    "tokensOwnedBitset": "0000000000",
    "builtCards": [
      "Clay Pool",
      "Workshop",
      "Clay Pit",
      "Tavern",
      "Clay Reserve",
      "Palisade",
      "Theater",
      "Stone Reserve",
      "Archery Range",
      "Sawmill",
      "Walls",
      "Dispensary",
      "Aqueduct",
      "Statue",
      "Forum",
      "Parade Ground",
      "Armory",
      "Palace",
      "Fortifications",
      "Circus"

    ],
    "wonders": [
      "The Statue of Zeus",
      "The Appian Way",
      "The Hanging Gardens",
      "Circus Maximus"

    ],
    "ownedTokens": [
      "Military Loss 2"

    ],
    "points": {
      "military": 13,
      "building": 60,
      "wonder": 0,
      "progress": 0,
      "total": 73

    }

  },
  "unusedCards": [
    {"age": "AGE_I", "name": "Apothecary"},
    {"age": "AGE_I", "name": "Baths"},
    {"age": "AGE_I", "name": "Quarry"},
    {"age": "AGE_II", "name": "Drying Room"},
    {"age": "AGE_II", "name": "School"},
    {"age": "AGE_II", "name": "Temple"},
    {"age": "AGE_III", "name": "Town Hall"},
    {"age": "AGE_III", "name": "Academy"},
    {"age": "AGE_III", "name": "Gardens"},
    {"age": "GUILD", "name": "Shipowners Guild"},
    {"age": "GUILD", "name": "Moneylenders Guild"},
    {"age": "GUILD", "name": "Scientists Guild"},
    {"age": "GUILD", "name": "Magistrates Guild"},
    {"age": "WONDER", "name": "The Great Library"},
    {"age": "WONDER", "name": "The Colossus"},
    {"age": "WONDER", "name": "Piraeus"},
    {"age": "WONDER", "name": "The Sphinx"}

  ],
  "discardedCards": [
    "Logging Camp",
    "Garrison",
    "Shelf Quarry",
    "Brewery",
    "Customs House",
    "Rostrum",
    "Stone Pit",
    "Traders Guild",
    "Glassworks",
    "Lighthouse",
    "University"

  ]

}
